medvision/__init__.py
medvision/__version__.py
medvision/annotation/__init__.py
medvision/annotation/mask2rws.py
medvision/annotation/rws.py
medvision/annotation/rws2dsmd.py
medvision/annotation/rws2mask.py
medvision/dataset/__init__.py
medvision/dataset/classification.py
medvision/dataset/detection.py
medvision/dataset/dsmd.py
medvision/dataset/segmentation.py
medvision/dataset/util.py
medvision/dicom/__init__.py
medvision/dicom/fileutil.py
medvision/dicom/io.py
medvision/evaluation/__init__.py
medvision/evaluation/compute_overlap.py
medvision/evaluation/eval_det.py
medvision/image/__init__.py
medvision/image/io.py
medvision/image/transforms/__init__.py
medvision/image/transforms/colorspace.py
medvision/image/transforms/geometry.py
medvision/image/transforms/normalize.py
medvision/network/__init__.py
medvision/network/download.py
medvision/util/__init__.py
medvision/util/encryption.py
medvision/util/fileutil.py
medvision/util/ftputil.py
medvision/util/multiprocessutil.py
medvision/util/timer.py
medvision/util/typeutil.py
medvision/visualization/__init__.py
medvision/visualization/draw_curve.py
medvision/visualization/image.py
medvision/visualization/plot_rws.py
medvision-1.0.1.dist-info/LICENSE
medvision-1.0.1.dist-info/METADATA
medvision-1.0.1.dist-info/WHEEL
medvision-1.0.1.dist-info/top_level.txt
medvision-1.0.1.dist-info/RECORD
