Metadata-Version: 2.1
Name: medvision
Version: 1.0.1
Summary: A python library for medical image computer vision.
Home-page: https://github.com/kyle0x54/medvision
Author: kyle0x54
Author-email: kyle0x54@163.com
License: APACHE
Classifier: Development Status :: 3 - Alpha
Classifier: License :: OSI Approved :: Apache Software License
Classifier: Operating System :: OS Independent
Classifier: Intended Audience :: Developers
Classifier: Topic :: Software Development :: Libraries :: Python Modules
Classifier: Programming Language :: Python :: 3
Classifier: Programming Language :: Python :: 3.6
Classifier: Programming Language :: Python :: 3.7
Requires-Python: >=3.6.0
License-File: LICENSE
Requires-Dist: matplotlib
Requires-Dist: natsort
Requires-Dist: numpy
Requires-Dist: opencv-python
Requires-Dist: pandas
Requires-Dist: pillow
Requires-Dist: pycryptodome
Requires-Dist: pydicom
Requires-Dist: scikit-learn
Requires-Dist: SimpleITK
Requires-Dist: tqdm
